README.md
setup.cfg
setup.py
distGaussianBinomial/Binomialdistribution.py
distGaussianBinomial/Gaussiandistribution.py
distGaussianBinomial/Generaldistribution.py
distGaussianBinomial/__init__.py
distGaussianBinomial.egg-info/PKG-INFO
distGaussianBinomial.egg-info/SOURCES.txt
distGaussianBinomial.egg-info/dependency_links.txt
distGaussianBinomial.egg-info/not-zip-safe
distGaussianBinomial.egg-info/top_level.txt