Metadata-Version: 1.0
Name: distGaussianBinomial
Version: 0.1
Summary: Gaussian and Binomial distributions
Home-page: UNKNOWN
Author: Megan Thong
Author-email: meganjythong@gmail.com
License: UNKNOWN
Platform: UNKNOWN
